channels_presence/__init__.py
channels_presence/apps.py
channels_presence/decorators.py
channels_presence/models.py
channels_presence/signals.py
channels_presence/tasks.py
channels_presence/management/__init__.py
channels_presence/management/commands/__init__.py
channels_presence/management/commands/prune_presences.py
channels_presence/management/commands/prune_rooms.py
channels_presence/migrations/0001_initial.py
channels_presence/migrations/__init__.py
django_channels_presence_4.0-1.1.2.dist-info/LICENSE
django_channels_presence_4.0-1.1.2.dist-info/METADATA
django_channels_presence_4.0-1.1.2.dist-info/WHEEL
django_channels_presence_4.0-1.1.2.dist-info/top_level.txt
django_channels_presence_4.0-1.1.2.dist-info/RECORD
